MANIFEST.in
setup.cfg
setup.py
gl_collector.egg-info/PKG-INFO
gl_collector.egg-info/SOURCES.txt
gl_collector.egg-info/dependency_links.txt
gl_collector.egg-info/requires.txt
gl_collector.egg-info/top_level.txt
glapi/__init__.py
glapi/glapi.py
glapi/metadata.json
glcollector/__init__.py
glcollector/commit.py
glcollector/group.py
glcollector/inject.py
glcollector/project.py
glcollector/settings.py
glcollector/sniff.py
glcollector/st_clean.py
glcollector/st_diff.py
glcollector/user.py
glcollector/utils.py