Metadata-Version: 1.0
Name: gl-collector
Version: 1.2.0
Summary: A project for Gitlab Collector Service
Home-page: https://github.com/SmartDeveloperHub/gitlab-collector
Author: Alejandro F. Carrera
Author-email: alejandro.fernandez.carrera@centeropenmiddleware.com
License: Apache 2
Keywords: inner-source collector gl-enhancer
Platform: UNKNOWN
